loc_authorities/__init__.py
loc_authorities/api.py
loc_authorities-0.2.0.dist-info/METADATA
loc_authorities-0.2.0.dist-info/WHEEL
loc_authorities-0.2.0.dist-info/licenses/LICENSE
loc_authorities-0.2.0.dist-info/RECORD
