Metadata-Version: 2.4
Name: loc-authorities
Version: 0.2.0
Summary: Python module for interacting with Library of Congress Linked Data Service and API endpoint
Project-URL: Documentation, https://americanphilosophicalsociety.github.io/loc-authorities/
Project-URL: Repository, https://github.com/AmericanPhilosophicalSociety/loc-authorities
Author-email: Center for Digital Scholarship at the American Philosophical Society <cds@amphilsoc.org>, David Ragnar Nelson <drnelson6@gmail.com>
License: Apache-2.0
License-File: LICENSE
Requires-Python: >=3.10
Requires-Dist: rdflib>=7.1.4
Requires-Dist: requests>=2.32.4
